{
    "frames": {
        "floor-1": {
            "frame": { "x": 0,"y": 0,"w": 64,"h": 64 }
        },
        "floor-2": {
            "frame": { "x": 65,"y": 0,"w": 64,"h": 64 }
        },
        "sw-s": {
            "frame": { "x": 0,"y": 100,"w": 100,"h": 100 }
        },
        "sw-w": {
            "frame": { "x": 100,"y": 100,"w": 100,"h": 100 }
        },
        "sw-n": {
            "frame": { "x": 200,"y": 100,"w": 100,"h": 100 }
        },
        "sw-e": {
            "frame": { "x": 300,"y": 100,"w": 100,"h": 100 }
        },
        "sc-nw": {
            "frame": { "x": 400,"y": 100,"w": 100,"h": 100 }
        },
        "sc-ne": {
            "frame": { "x": 500,"y": 100,"w": 100,"h": 100 }
        },
        "sc-sw": {
            "frame": { "x": 600,"y": 100,"w": 100,"h": 100 }
        },
        "sc-se": {
            "frame": { "x": 700,"y": 100,"w": 100,"h": 100 }
        },
        "chest-east": {
            "frame": { "x": 0,"y": 200,"w": 64,"h": 74 }
        },
        "chest-open-east": {
            "frame": { "x": 64,"y": 200,"w": 64,"h": 74 }
        },
        "door-south": {
            "frame": { "x": 0,"y": 274,"w": 100,"h": 100 }
        },
        "door-open-south": {
            "frame": { "x": 100,"y": 274,"w": 100,"h": 100 }
        },
        "door-east": {
            "frame": { "x": 200,"y": 274,"w": 100,"h": 100 }
        },
        "door-open-east": {
            "frame": { "x": 300,"y": 274,"w": 100,"h": 100 }
        },
        "key": {
            "frame": { "x": 0, "y": 398, "w": 100 , "h": 44 }
        },
        "paper": {
            "frame": { "x": 235, "y": 395, "w": 50, "h": 60 }
        },
        "book": {
            "frame": { "x": 316, "y": 385, "w": 66 , "h": 80 }
        },
        "book-open-east": {
            "frame": { "x": 103, "y": 396, "w": 100 , "h": 50 }
        },
        "table-south": {
            "frame": { "x": 0, "y": 476, "w": 138 , "h": 75 }
        },
        "table-west": {
            "frame": { "x": 138, "y": 476, "w": 75 , "h": 138 }
        },
        "bookshelf-east": {
            "frame": { "x": 0, "y": 663, "w": 100 , "h": 100 }
        },
        "bookshelf-south": {
            "frame": { "x": 100, "y": 663, "w": 100 , "h": 100 }
        },
        "chair_01-north": {
            "frame": { "x": 0, "y": 763, "w": 75 , "h": 64 }
        },
        "chair_01-west": {
            "frame": { "x": 76, "y": 763, "w": 65 , "h": 75 }
        }
    }
}